[
  {
    "date": "2025-04-08",
    "highNum": "0",
    "lowNum": "4.46",
    "reading": "4.46"
  },
  {
    "date": "2025-04-07",
    "highNum": "0",
    "lowNum": "3.35",
    "reading": "3.35"
  },
  {
    "date": "2025-04-06",
    "highNum": "0",
    "lowNum": "2.79",
    "reading": "2.79"
  },
  {
    "date": "2025-04-05",
    "highNum": "7.89",
    "lowNum": "5.7",
    "reading": "13.59"
  },
  {
    "date": "2025-04-04",
    "highNum": "0",
    "lowNum": "3.42",
    "reading": "3.42"
  },
  {
    "date": "2025-04-03",
    "highNum": "0",
    "lowNum": "0",
    "reading": "0"
  }
]